emds
